azdo_wiki_tools/__init__.py
azdo_wiki_tools/extractor.py
azdo_wiki_tools-0.1.1.dist-info/LICENSE
azdo_wiki_tools-0.1.1.dist-info/METADATA
azdo_wiki_tools-0.1.1.dist-info/WHEEL
azdo_wiki_tools-0.1.1.dist-info/RECORD
