Metadata-Version: 2.1
Name: azdo-wiki-tools
Version: 0.1.1
Summary: A collection of tools that consume data from Azure DevOps Wikis.
Author: Dean Phillips
Author-email: dean.phillips@e-hps.com
Requires-Python: >=3.12,<4.0
Classifier: Programming Language :: Python :: 3
Classifier: Programming Language :: Python :: 3.12
Requires-Dist: python-dotenv (>=1.0.1,<2.0.0)
Requires-Dist: requests (>=2.31.0,<3.0.0)
